Workbook

Sheet DailySales
A1: Category | B1: Item | C1: Price | D1: Cash Qty | E1: Cash Sales | F1: GCash Qty | G1: GCash Sales | H1: Foodpanda Qty | I1: Foodpanda Sales | J1: Total Qty | K1: Total Sales | L1: Date
A2: Ala Carte | B2: Korean Spicy Chicken | C2: 189 | E2: =C2*D2 -> 0 | G2: =C2*F2 -> 0 | I2: =C2*H2 -> 0 | J2: =D2+F2+H2 -> 0 | K2: =E2+G2+I2 -> 0
A3: Ala Carte | B3: Korean Spicy Pork | C3: 189 | E3: =C3*D3 -> 0 | F3: 1 | G3: =C3*F3 -> 189 | I3: =C3*H3 -> 0 | J3: =D3+F3+H3 -> 1 | K3: =E3+G3+I3 -> 189
A4: Ala Carte | B4: Beef Bulgogi | C4: 189 | E4: =C4*D4 -> 0 | G4: =C4*F4 -> 0 | I4: =C4*H4 -> 0 | J4: =D4+F4+H4 -> 0 | K4: =E4+G4+I4 -> 0
A5: Ala Carte | B5: Teokbokki (Rice cake) | C5: 189 | E5: =C5*D5 -> 0 | G5: =C5*F5 -> 0 | I5: =C5*H5 -> 0 | J5: =D5+F5+H5 -> 0 | K5: =E5+G5+I5 -> 0
A6: Ala Carte | B6: Spicy Cheesy Chicken | C6: 189 | E6: =C6*D6 -> 0 | G6: =C6*F6 -> 0 | I6: =C6*H6 -> 0 | J6: =D6+F6+H6 -> 0 | K6: =E6+G6+I6 -> 0
A7: Ala Carte | B7: Bam-E | C7: 189 | E7: =C7*D7 -> 0 | G7: =C7*F7 -> 0 | I7: =C7*H7 -> 0 | J7: =D7+F7+H7 -> 0 | K7: =E7+G7+I7 -> 0
A8: Ala Carte | B8: Pork Binagoongan | C8: 189 | E8: =C8*D8 -> 0 | G8: =C8*F8 -> 0 | I8: =C8*H8 -> 0 | J8: =D8+F8+H8 -> 0 | K8: =E8+G8+I8 -> 0
A9: Ala Carte | B9: Pork Sisig | C9: 189 | D9: 1 | E9: =C9*D9 -> 189 | G9: =C9*F9 -> 0 | I9: =C9*H9 -> 0 | J9: =D9+F9+H9 -> 1 | K9: =E9+G9+I9 -> 189
A10: Sizzlers (Unli Rice + 1 Free Drink) | B10: Pork Sisig | C10: 149 | E10: =C10*D10 -> 0 | F10: 1 | G10: =C10*F10 -> 149 | I10: =C10*H10 -> 0 | J10: =D10+F10+H10 -> 1 | K10: =E10+G10+I10 -> 149
A11: Sizzlers (Unli Rice + 1 Free Drink) | B11: Chicken Sisig | C11: 149 | E11: =C11*D11 -> 0 | G11: =C11*F11 -> 0 | I11: =C11*H11 -> 0 | J11: =D11+F11+H11 -> 0 | K11: =E11+G11+I11 -> 0
A12: Sizzlers (Unli Rice + 1 Free Drink) | B12: Squid Sisig | C12: 149 | E12: =C12*D12 -> 0 | G12: =C12*F12 -> 0 | I12: =C12*H12 -> 0 | J12: =D12+F12+H12 -> 0 | K12: =E12+G12+I12 -> 0
A13: Sizzlers (Unli Rice + 1 Free Drink) | B13: Korean Spicy Pork | C13: 149 | E13: =C13*D13 -> 0 | G13: =C13*F13 -> 0 | I13: =C13*H13 -> 0 | J13: =D13+F13+H13 -> 0 | K13: =E13+G13+I13 -> 0
A14: Sizzlers (Unli Rice + 1 Free Drink) | B14: Porkchop | C14: 149 | G14: =C14*F14 -> 0 | I14: =C14*H14 -> 0 | J14: =D14+F14+H14 -> 0 | K14: =E14+G14+I14 -> 0
A15: Sizzlers (Unli Rice + 1 Free Drink) | B15: Pork Liempo | C15: 149 | E15: =C15*D15 -> 0 | G15: =C15*F15 -> 0 | I15: =C15*H15 -> 0 | J15: =D15+F15+H15 -> 0 | K15: =E15+G15+I15 -> 0
A16: Sizzlers (Unli Rice + 1 Free Drink) | B16: Pork steak | C16: 149 | E16: =C16*D16 -> 0 | G16: =C16*F16 -> 0 | I16: =C16*H16 -> 0 | J16: =D16+F16+H16 -> 0 | K16: =E16+G16+I16 -> 0
A17: Sizzlers (Unli Rice + 1 Free Drink) | B17: Beef Steak | C17: 149 | E17: =C17*D17 -> 0 | G17: =C17*F17 -> 0 | I17: =C17*H17 -> 0 | J17: =D17+F17+H17 -> 0 | K17: =E17+G17+I17 -> 0
A18: Sizzlers (Unli Rice + 1 Free Drink) | B18: Burger Steak | C18: 149 | E18: =C18*D18 -> 0 | G18: =C18*F18 -> 0 | I18: =C18*H18 -> 0 | J18: =D18+F18+H18 -> 0 | K18: =E18+G18+I18 -> 0
A19: Sizzlers (Unli Rice + 1 Free Drink) | B19: Fried Chicken | C19: 149 | E19: =C19*D19 -> 0 | F19: 1 | G19: =C19*F19 -> 149 | I19: =C19*H19 -> 0 | J19: =D19+F19+H19 -> 1 | K19: =E19+G19+I19 -> 149
A20: Sizzlers (Unli Rice + 1 Free Drink) | B20: Beef Ala Pobre | C20: 149 | E20: =C20*D20 -> 0 | G20: =C20*F20 -> 0 | I20: =C20*H20 -> 0 | J20: =D20+F20+H20 -> 0 | K20: =E20+G20+I20 -> 0
A21: Sizzlers (Unli Rice + 1 Free Drink) | B21: Fish Fillet | C21: 149 | E21: =C21*D21 -> 0 | G21: =C21*F21 -> 0 | I21: =C21*H21 -> 0 | J21: =D21+F21+H21 -> 0 | K21: =E21+G21+I21 -> 0
A22: Sizzlers (Unli Rice + 1 Free Drink) | B22: Squid rings | C22: 149 | E22: =C22*D22 -> 0 | G22: =C22*F22 -> 0 | I22: =C22*H22 -> 0 | J22: =D22+F22+H22 -> 0 | K22: =E22+G22+I22 -> 0
A23: Classic Cutlets | B23: Fish Cutlet | C23: 159 | D23: 1 | E23: =C23*D23 -> 159 | G23: =C23*F23 -> 0 | I23: =C23*H23 -> 0 | J23: =D23+F23+H23 -> 1 | K23: =E23+G23+I23 -> 159
A24: Classic Cutlets | B24: Pork Cutlet | C24: 159 | D24: 2 | E24: =C24*D24 -> 318 | F24: 1 | G24: =C24*F24 -> 159 | I24: =C24*H24 -> 0 | J24: =D24+F24+H24 -> 3 | K24: =E24+G24+I24 -> 477
A25: Classic Cutlets | B25: Chicken Cutlet | C25: 159 | E25: =C25*D25 -> 0 | F25: 1 | G25: =C25*F25 -> 159 | I25: =C25*H25 -> 0 | J25: =D25+F25+H25 -> 1 | K25: =E25+G25+I25 -> 159
A26: Classic Cutlets | B26: Beef Cutlet | C26: 159 | E26: =C26*D26 -> 0 | G26: =C26*F26 -> 0 | I26: =C26*H26 -> 0 | J26: =D26+F26+H26 -> 0 | K26: =E26+G26+I26 -> 0
A27: Rice Toppings (Fried Rice) | B27: Fish Fillet | C27: 99 | E27: =C27*D27 -> 0 | G27: =C27*F27 -> 0 | I27: =C27*H27 -> 0 | J27: =D27+F27+H27 -> 0 | K27: =E27+G27+I27 -> 0
A28: Rice Toppings (Fried Rice) | B28: Porkchop | C28: 99 | E28: =C28*D28 -> 0 | G28: =C28*F28 -> 0 | I28: =C28*H28 -> 0 | J28: =D28+F28+H28 -> 0 | K28: =E28+G28+I28 -> 0
A29: Rice Toppings (Fried Rice) | B29: Siomai | C29: 99 | E29: =C29*D29 -> 0 | G29: =C29*F29 -> 0 | I29: =C29*H29 -> 0 | J29: =D29+F29+H29 -> 0 | K29: =E29+G29+I29 -> 0
A30: Rice Toppings (Fried Rice) | B30: Sisig | C30: 99 | D30: 1 | E30: =C30*D30 -> 99 | G30: =C30*F30 -> 0 | I30: =C30*H30 -> 0 | J30: =D30+F30+H30 -> 1 | K30: =E30+G30+I30 -> 99
A31: Rice Toppings (Fried Rice) | B31: Chicken Nuggets | C31: 99 | E31: =C31*D31 -> 0 | G31: =C31*F31 -> 0 | I31: =C31*H31 -> 0 | J31: =D31+F31+H31 -> 0 | K31: =E31+G31+I31 -> 0
A32: Appetizers | B32: Egg roll | C32: 149 | E32: =C32*D32 -> 0 | G32: =C32*F32 -> 0 | I32: =C32*H32 -> 0 | J32: =D32+F32+H32 -> 0 | K32: =E32+G32+I32 -> 0
A33: Appetizers | B33: Kimbap | C33: 149 | E33: =C33*D33 -> 0 | G33: =C33*F33 -> 0 | I33: =C33*H33 -> 0 | J33: =D33+F33+H33 -> 0 | K33: =E33+G33+I33 -> 0
A34: Appetizers | B34: Steam Egg | C34: 149 | E34: =C34*D34 -> 0 | G34: =C34*F34 -> 0 | I34: =C34*H34 -> 0 | J34: =D34+F34+H34 -> 0 | K34: =E34+G34+I34 -> 0
A35: Appetizers | B35: Black Noodles | C35: 149 | E35: =C35*D35 -> 0 | G35: =C35*F35 -> 0 | I35: =C35*H35 -> 0 | J35: =D35+F35+H35 -> 0 | K35: =E35+G35+I35 -> 0
A36: Drinks & Extras | B36: Mt dew | C36: 25 | E36: =C36*D36 -> 0 | G36: =C36*F36 -> 0 | I36: =C36*H36 -> 0 | J36: =D36+F36+H36 -> 0 | K36: =E36+G36+I36 -> 0
A37: Drinks & Extras | B37: Pepsi | C37: 20 | D37: 2 | E37: =C37*D37 -> 40 | G37: =C37*F37 -> 0 | I37: =C37*H37 -> 0 | J37: =D37+F37+H37 -> 2 | K37: =E37+G37+I37 -> 40
A38: Drinks & Extras | B38: Bottled Water | C38: 20 | E38: =C38*D38 -> 0 | G38: =C38*F38 -> 0 | I38: =C38*H38 -> 0 | J38: =D38+F38+H38 -> 0 | K38: =E38+G38+I38 -> 0
A39: Drinks & Extras | B39: Plain Rice | C39: 20 | E39: =C39*D39 -> 0 | G39: =C39*F39 -> 0 | I39: =C39*H39 -> 0 | J39: =D39+F39+H39 -> 0 | K39: =E39+G39+I39 -> 0
A40: Drinks & Extras | B40: Garlic Rice | C40: 25 | E40: =C40*D40 -> 0 | G40: =C40*F40 -> 0 | I40: =C40*H40 -> 0 | J40: =D40+F40+H40 -> 0 | K40: =E40+G40+I40 -> 0
A41: Drinks & Extras | B41: Egg | C41: 20 | E41: =C41*D41 -> 0 | G41: =C41*F41 -> 0 | I41: =C41*H41 -> 0 | J41: =D41+F41+H41 -> 0 | K41: =E41+G41+I41 -> 0
A42: Soup and Stews | B42: Beef Pares | C42: 149 | E42: =C42*D42 -> 0 | G42: =C42*F42 -> 0 | I42: =C42*H42 -> 0 | J42: =D42+F42+H42 -> 0 | K42: =E42+G42+I42 -> 0
A43: Soup and Stews | B43: Beef Mami | C43: 149 | E43: =C43*D43 -> 0 | G43: =C43*F43 -> 0 | I43: =C43*H43 -> 0 | J43: =D43+F43+H43 -> 0 | K43: =E43+G43+I43 -> 0
A44: Soup and Stews | B44: Pork Ramen | C44: 149 | E44: =C44*D44 -> 0 | G44: =C44*F44 -> 0 | I44: =C44*H44 -> 0 | J44: =D44+F44+H44 -> 0 | K44: =E44+G44+I44 -> 0
A45: TOTAL | E45: =SUM(E2:E44) -> 805 | G45: =SUM(G2:G44) -> 805 | I45: =SUM(I2:I44) -> 0 | J45: =SUM(J2:J44) -> 12 | K45: =SUM(K2:K44) -> 1610 | L45: 46001
A47: Category | B47: Item | C47: Price | D47: Cash Qty | E47: Cash Sales | F47: GCash Qty | G47: GCash Sales | H47: Foodpanda Qty | I47: Foodpanda Sales | J47: Total Qty | K47: Total Sales | L47: Date
A48: Ala Carte | B48: Korean Spicy Chicken | C48: 189 | E48: =C48*D48 -> 0 | G48: =C48*F48 -> 0 | I48: =C48*H48 -> 0 | J48: =D48+F48+H48 -> 0 | K48: =E48+G48+I48 -> 0
A49: Ala Carte | B49: Korean Spicy Pork | C49: 189 | E49: =C49*D49 -> 0 | G49: =C49*F49 -> 0 | I49: =C49*H49 -> 0 | J49: =D49+F49+H49 -> 0 | K49: =E49+G49+I49 -> 0
A50: Ala Carte | B50: Beef Bulgogi | C50: 189 | E50: =C50*D50 -> 0 | G50: =C50*F50 -> 0 | I50: =C50*H50 -> 0 | J50: =D50+F50+H50 -> 0 | K50: =E50+G50+I50 -> 0
A51: Ala Carte | B51: Teokbokki (Rice cake) | C51: 189 | E51: =C51*D51 -> 0 | G51: =C51*F51 -> 0 | I51: =C51*H51 -> 0 | J51: =D51+F51+H51 -> 0 | K51: =E51+G51+I51 -> 0
A52: Ala Carte | B52: Spicy Cheesy Chicken | C52: 189 | E52: =C52*D52 -> 0 | G52: =C52*F52 -> 0 | I52: =C52*H52 -> 0 | J52: =D52+F52+H52 -> 0 | K52: =E52+G52+I52 -> 0
A53: Ala Carte | B53: Bam-E | C53: 189 | E53: =C53*D53 -> 0 | G53: =C53*F53 -> 0 | I53: =C53*H53 -> 0 | J53: =D53+F53+H53 -> 0 | K53: =E53+G53+I53 -> 0
A54: Ala Carte | B54: Pork Binagoongan | C54: 189 | E54: =C54*D54 -> 0 | G54: =C54*F54 -> 0 | I54: =C54*H54 -> 0 | J54: =D54+F54+H54 -> 0 | K54: =E54+G54+I54 -> 0
A55: Ala Carte | B55: Pork Sisig | C55: 189 | E55: =C55*D55 -> 0 | G55: =C55*F55 -> 0 | I55: =C55*H55 -> 0 | J55: =D55+F55+H55 -> 0 | K55: =E55+G55+I55 -> 0
A56: Sizzlers (Unli Rice + 1 Free Drink) | B56: Pork Sisig | C56: 149 | D56: 1 | E56: =C56*D56 -> 149 | G56: =C56*F56 -> 0 | I56: =C56*H56 -> 0 | J56: =D56+F56+H56 -> 1 | K56: =E56+G56+I56 -> 149
A57: Sizzlers (Unli Rice + 1 Free Drink) | B57: Chicken Sisig | C57: 149 | D57: 1 | E57: =C57*D57 -> 149 | G57: =C57*F57 -> 0 | I57: =C57*H57 -> 0 | J57: =D57+F57+H57 -> 1 | K57: =E57+G57+I57 -> 149
A58: Sizzlers (Unli Rice + 1 Free Drink) | B58: Squid Sisig | C58: 149 | E58: =C58*D58 -> 0 | G58: =C58*F58 -> 0 | I58: =C58*H58 -> 0 | J58: =D58+F58+H58 -> 0 | K58: =E58+G58+I58 -> 0
A59: Sizzlers (Unli Rice + 1 Free Drink) | B59: Korean Spicy Pork | C59: 149 | D59: 1 | E59: =C59*D59 -> 149 | G59: =C59*F59 -> 0 | I59: =C59*H59 -> 0 | J59: =D59+F59+H59 -> 1 | K59: =E59+G59+I59 -> 149
A60: Sizzlers (Unli Rice + 1 Free Drink) | B60: Porkchop | C60: 149 | E60: =C60*D60 -> 0 | G60: =C60*F60 -> 0 | H60: 1 | I60: =C60*H60 -> 149 | J60: =D60+F60+H60 -> 1 | K60: =E60+G60+I60 -> 149
A61: Sizzlers (Unli Rice + 1 Free Drink) | B61: Pork Liempo | C61: 149 | D61: 2 | E61: =C61*D61 -> 298 | G61: =C61*F61 -> 0 | I61: =C61*H61 -> 0 | J61: =D61+F61+H61 -> 2 | K61: =E61+G61+I61 -> 298
A62: Sizzlers (Unli Rice + 1 Free Drink) | B62: Pork steak | C62: 149 | E62: =C62*D62 -> 0 | G62: =C62*F62 -> 0 | I62: =C62*H62 -> 0 | J62: =D62+F62+H62 -> 0 | K62: =E62+G62+I62 -> 0
A63: Sizzlers (Unli Rice + 1 Free Drink) | B63: Beef Steak | C63: 149 | E63: =C63*D63 -> 0 | G63: =C63*F63 -> 0 | I63: =C63*H63 -> 0 | J63: =D63+F63+H63 -> 0 | K63: =E63+G63+I63 -> 0
A64: Sizzlers (Unli Rice + 1 Free Drink) | B64: Burger Steak | C64: 149 | E64: =C64*D64 -> 0 | G64: =C64*F64 -> 0 | I64: =C64*H64 -> 0 | J64: =D64+F64+H64 -> 0 | K64: =E64+G64+I64 -> 0
A65: Sizzlers (Unli Rice + 1 Free Drink) | B65: Fried Chicken | C65: 149 | E65: =C65*D65 -> 0 | G65: =C65*F65 -> 0 | I65: =C65*H65 -> 0 | J65: =D65+F65+H65 -> 0 | K65: =E65+G65+I65 -> 0
A66: Sizzlers (Unli Rice + 1 Free Drink) | B66: Beef Ala Pobre | C66: 149 | E66: =C66*D66 -> 0 | G66: =C66*F66 -> 0 | H66: 1 | I66: =C66*H66 -> 149 | J66: =D66+F66+H66 -> 1 | K66: =E66+G66+I66 -> 149
A67: Sizzlers (Unli Rice + 1 Free Drink) | B67: Fish Fillet | C67: 149 | E67: =C67*D67 -> 0 | G67: =C67*F67 -> 0 | I67: =C67*H67 -> 0 | J67: =D67+F67+H67 -> 0 | K67: =E67+G67+I67 -> 0
A68: Sizzlers (Unli Rice + 1 Free Drink) | B68: Squid rings | C68: 149 | E68: =C68*D68 -> 0 | G68: =C68*F68 -> 0 | I68: =C68*H68 -> 0 | J68: =D68+F68+H68 -> 0 | K68: =E68+G68+I68 -> 0
A69: Classic Cutlets | B69: Fish Cutlet | C69: 159 | E69: =C69*D69 -> 0 | G69: =C69*F69 -> 0 | I69: =C69*H69 -> 0 | J69: =D69+F69+H69 -> 0 | K69: =E69+G69+I69 -> 0
A70: Classic Cutlets | B70: Pork Cutlet | C70: 159 | E70: =C70*D70 -> 0 | G70: =C70*F70 -> 0 | I70: =C70*H70 -> 0 | J70: =D70+F70+H70 -> 0 | K70: =E70+G70+I70 -> 0
A71: Classic Cutlets | B71: Chicken Cutlet | C71: 159 | E71: =C71*D71 -> 0 | G71: =C71*F71 -> 0 | I71: =C71*H71 -> 0 | J71: =D71+F71+H71 -> 0 | K71: =E71+G71+I71 -> 0
A72: Classic Cutlets | B72: Beef Cutlet | C72: 159 | E72: =C72*D72 -> 0 | G72: =C72*F72 -> 0 | I72: =C72*H72 -> 0 | J72: =D72+F72+H72 -> 0 | K72: =E72+G72+I72 -> 0
A73: Rice Toppings (Fried Rice) | B73: Fish Fillet | C73: 99 | E73: =C73*D73 -> 0 | G73: =C73*F73 -> 0 | H73: 1 | I73: =C73*H73 -> 99 | J73: =D73+F73+H73 -> 1 | K73: =E73+G73+I73 -> 99
A74: Rice Toppings (Fried Rice) | B74: Porkchop | C74: 99 | D74: 1 | E74: =C74*D74 -> 99 | G74: =C74*F74 -> 0 | I74: =C74*H74 -> 0 | J74: =D74+F74+H74 -> 1 | K74: =E74+G74+I74 -> 99
A75: Rice Toppings (Fried Rice) | B75: Siomai | C75: 99 | E75: =C75*D75 -> 0 | G75: =C75*F75 -> 0 | I75: =C75*H75 -> 0 | J75: =D75+F75+H75 -> 0 | K75: =E75+G75+I75 -> 0
A76: Rice Toppings (Fried Rice) | B76: Sisig | C76: 99 | E76: =C76*D76 -> 0 | G76: =C76*F76 -> 0 | I76: =C76*H76 -> 0 | J76: =D76+F76+H76 -> 0 | K76: =E76+G76+I76 -> 0
A77: Rice Toppings (Fried Rice) | B77: Chicken Nuggets | C77: 99 | E77: =C77*D77 -> 0 | G77: =C77*F77 -> 0 | I77: =C77*H77 -> 0 | J77: =D77+F77+H77 -> 0 | K77: =E77+G77+I77 -> 0
A78: Appetizers | B78: Egg roll | C78: 149 | E78: =C78*D78 -> 0 | G78: =C78*F78 -> 0 | I78: =C78*H78 -> 0 | J78: =D78+F78+H78 -> 0 | K78: =E78+G78+I78 -> 0
A79: Appetizers | B79: Kimbap | C79: 149 | E79: =C79*D79 -> 0 | G79: =C79*F79 -> 0 | I79: =C79*H79 -> 0 | J79: =D79+F79+H79 -> 0 | K79: =E79+G79+I79 -> 0
A80: Appetizers | B80: Steam Egg | C80: 149 | E80: =C80*D80 -> 0 | G80: =C80*F80 -> 0 | I80: =C80*H80 -> 0 | J80: =D80+F80+H80 -> 0 | K80: =E80+G80+I80 -> 0
A81: Appetizers | B81: Black Noodles | C81: 149 | E81: =C81*D81 -> 0 | G81: =C81*F81 -> 0 | I81: =C81*H81 -> 0 | J81: =D81+F81+H81 -> 0 | K81: =E81+G81+I81 -> 0
A82: Drinks & Extras | B82: Mt dew | C82: 25 | E82: =C82*D82 -> 0 | G82: =C82*F82 -> 0 | I82: =C82*H82 -> 0 | J82: =D82+F82+H82 -> 0 | K82: =E82+G82+I82 -> 0
A83: Drinks & Extras | B83: Pepsi | C83: 20 | D83: 4 | E83: =C83*D83 -> 80 | G83: =C83*F83 -> 0 | I83: =C83*H83 -> 0 | J83: =D83+F83+H83 -> 4 | K83: =E83+G83+I83 -> 80
A84: Drinks & Extras | B84: Bottled Water | C84: 20 | E84: =C84*D84 -> 0 | G84: =C84*F84 -> 0 | I84: =C84*H84 -> 0 | J84: =D84+F84+H84 -> 0 | K84: =E84+G84+I84 -> 0
A85: Drinks & Extras | B85: Plain Rice | C85: 20 | E85: =C85*D85 -> 0 | G85: =C85*F85 -> 0 | H85: 4 | I85: =C85*H85 -> 80 | J85: =D85+F85+H85 -> 4 | K85: =E85+G85+I85 -> 80
A86: Drinks & Extras | B86: Garlic Rice | C86: 25 | E86: =C86*D86 -> 0 | G86: =C86*F86 -> 0 | I86: =C86*H86 -> 0 | J86: =D86+F86+H86 -> 0 | K86: =E86+G86+I86 -> 0
A87: Drinks & Extras | B87: Egg | C87: 20 | D87: 1 | E87: =C87*D87 -> 20 | G87: =C87*F87 -> 0 | I87: =C87*H87 -> 0 | J87: =D87+F87+H87 -> 1 | K87: =E87+G87+I87 -> 20
A88: Soup and Stews | B88: Beef Pares | C88: 149 | E88: =C88*D88 -> 0 | G88: =C88*F88 -> 0 | I88: =C88*H88 -> 0 | J88: =D88+F88+H88 -> 0 | K88: =E88+G88+I88 -> 0
A89: Soup and Stews | B89: Beef Mami | C89: 149 | E89: =C89*D89 -> 0 | G89: =C89*F89 -> 0 | I89: =C89*H89 -> 0 | J89: =D89+F89+H89 -> 0 | K89: =E89+G89+I89 -> 0
A90: Soup and Stews | B90: Pork Ramen | C90: 149 | E90: =C90*D90 -> 0 | G90: =C90*F90 -> 0 | I90: =C90*H90 -> 0 | J90: =D90+F90+H90 -> 0 | K90: =E90+G90+I90 -> 0
A91: TOTAL | E91: =SUM(E48:E90) -> 944 | G91: =SUM(G48:G90) -> 0 | I91: =SUM(I48:I90) -> 477 | J91: =SUM(J48:J90) -> 18 | K91: =SUM(K48:K90) -> 1421 | L91: 46002
A93: Category | B93: Item | C93: Price | D93: Cash Qty | E93: Cash Sales | F93: GCash Qty | G93: GCash Sales | H93: Foodpanda Qty | I93: Foodpanda Sales | J93: Total Qty | K93: Total Sales | L93: Date
A94: Ala Carte | B94: Korean Spicy Chicken | C94: 189 | E94: =C94*D94 -> 0 | G94: =C94*F94 -> 0 | I94: =C94*H94 -> 0 | J94: =D94+F94+H94 -> 0 | K94: =E94+G94+I94 -> 0
A95: Ala Carte | B95: Korean Spicy Pork | C95: 189 | E95: =C95*D95 -> 0 | G95: =C95*F95 -> 0 | I95: =C95*H95 -> 0 | J95: =D95+F95+H95 -> 0 | K95: =E95+G95+I95 -> 0
A96: Ala Carte | B96: Beef Bulgogi | C96: 189 | E96: =C96*D96 -> 0 | G96: =C96*F96 -> 0 | I96: =C96*H96 -> 0 | J96: =D96+F96+H96 -> 0 | K96: =E96+G96+I96 -> 0
A97: Ala Carte | B97: Teokbokki (Rice cake) | C97: 189 | E97: =C97*D97 -> 0 | G97: =C97*F97 -> 0 | I97: =C97*H97 -> 0 | J97: =D97+F97+H97 -> 0 | K97: =E97+G97+I97 -> 0
A98: Ala Carte | B98: Spicy Cheesy Chicken | C98: 189 | E98: =C98*D98 -> 0 | G98: =C98*F98 -> 0 | I98: =C98*H98 -> 0 | J98: =D98+F98+H98 -> 0 | K98: =E98+G98+I98 -> 0
A99: Ala Carte | B99: Bam-E | C99: 189 | E99: =C99*D99 -> 0 | G99: =C99*F99 -> 0 | I99: =C99*H99 -> 0 | J99: =D99+F99+H99 -> 0 | K99: =E99+G99+I99 -> 0
A100: Ala Carte | B100: Pork Binagoongan | C100: 189 | E100: =C100*D100 -> 0 | G100: =C100*F100 -> 0 | I100: =C100*H100 -> 0 | J100: =D100+F100+H100 -> 0 | K100: =E100+G100+I100 -> 0
A101: Ala Carte | B101: Pork Sisig | C101: 189 | D101: 1 | E101: =C101*D101 -> 189 | F101: 1 | G101: =C101*F101 -> 189 | I101: =C101*H101 -> 0 | J101: =D101+F101+H101 -> 2 | K101: =E101+G101+I101 -> 378
A102: Sizzlers (Unli Rice + 1 Free Drink) | B102: Pork Sisig | C102: 149 | D102: 1 | E102: =C102*D102 -> 149 | F102: 1 | G102: =C102*F102 -> 149 | I102: =C102*H102 -> 0 | J102: =D102+F102+H102 -> 2 | K102: =E102+G102+I102 -> 298
...

Sheet DailySummary
A1: Date | B1: Cash Sales | C1: GCash Sales | D1: Foodpanda Sales | E1: Total Sales | F1: Remarks
A2: 45902 | B2: 1800 | C2: 149 | D2: 0 | E2: =SUM(B2:C2:D2) -> 1949
A3: 45903 | B3: 2035 | C3: 457 | D3: 0 | E3: =SUM(B3:C3:D3) -> 2492
A4: 45904 | B4: 1500 | C4: 0 | D4: 338 | E4: =SUM(B4:C4:D4) -> 1838
A5: 45905 | B5: 2978 | C5: 0 | D5: 0 | E5: =SUM(B5:C5:D5) -> 2978
A6: 45906 | B6: 0 | C6: 1023 | D6: 0 | E6: =SUM(B6:C6:D6) -> 1023
A7: 45907 | B7: 0 | C7: 0 | D7: 0 | E7: =SUM(B7:C7:D7) -> 0 | F7: closed
A8: 45908 | B8: 0 | C8: 0 | D8: 0 | E8: =SUM(B8:C8:D8) -> 0 | F8: closed
A9: 45909 | B9: 1000 | C9: 0 | D9: 0 | E9: =SUM(B9:C9:D9) -> 1000
A10: 45910 | B10: 298 | C10: 234 | D10: 0 | E10: =SUM(B10:C10:D10) -> 532
A11: 45911 | B11: 1420 | C11: 0 | D11: 0 | E11: =SUM(B11:C11:D11) -> 1420
A12: 45912 | B12: 0 | C12: 0 | D12: 0 | E12: =SUM(B12:C12:D12) -> 0
A13: 45913 | B13: 1089 | C13: 0 | D13: 0 | E13: =SUM(B13:C13:D13) -> 1089
A14: 45914 | B14: 0 | C14: 0 | D14: 0 | E14: =SUM(B14:C14:D14) -> 0
A15: 45915 | B15: 1613 | C15: 0 | D15: 0 | E15: =SUM(B15:C15:D15) -> 1613
A16: 45916 | B16: 1889 | C16: 0 | D16: 0 | E16: =SUM(B16:C16:D16) -> 1889
A17: 45917 | B17: 1200 | C17: 0 | D17: 567 | E17: =SUM(B17:C17:D17) -> 1767
A18: 45918 | B18: 2150 | C18: 0 | D18: 2126 | E18: =SUM(B18:C18:D18) -> 4276
A19: 45919 | B19: 1200 | C19: 477 | D19: 934 | E19: =SUM(B19:C19:D19) -> 2611
A20: 45920 | B20: 800 | C20: 318 | D20: 0 | E20: =SUM(B20:C20:D20) -> 1118
... A30: 45930 | B30: 1600 | C30: 0 | D30: 0 | E30: =SUM(B30:C30:D30) -> 1600
A31: Total | B31: 29497 | C31: 3495 | D31: 5920 | E31: =SUM(E2:E30) -> 38912
A32: Date | B32: Cash Sales | C32: GCash Sales | D32: Food panda Sales | E32: Total Sales | F32: Remarks
A33: 45931 | B33: 1400 | C33: 0 | D33: 338 | E33: =sum(B33:C33:D33) -> 1738
A34: 45932 | B34: 1900 | C34: 298 | D34: 338 | E34: =sum(B34:C34:D34) -> 2536
A35: 45933 | B35: 659 | C35: 496 | D35: 0 | E35: =sum(B35:C35:D35) -> 1155
A36: 45934 | B36: 576 | C36: 0 | D36: 0 | E36: =sum(B36:C36:D36) -> 576
A37: 45935 | B37: 0 | C37: 0 | D37: 0 | E37: =sum(B37:C37:D37) -> 0
A38: 45936 | B38: 1490 | C38: 149 | D38: 0 | E38: =sum(B38:C38:D38) -> 1639
A39: 45937 | B39: 0 | C39: 0 | D39: 0 | E39: =sum(B39:C39:D39) -> 0
A40: 45938 | B40: 850 | C40: 0 | D40: 149 | E40: =sum(B40:C40:D40) -> 999
A41: 45939 | B41: 567 | C41: 447 | D41: 0 | E41: =sum(B41:C41:D41) -> 1014
A42: 45940 | B42: 500 | C42: 0 | D42: 0 | E42: =sum(B42:C42:D42) -> 500
A43: 45941 | B43: 900 | C43: 0 | D43: 0 | E43: =sum(B43:C43:D43) -> 900
A44: 45942 | B44: 0 | C44: 0 | D44: 0 | E44: =sum(B44:C44:D44) -> 0 | F44: closed
A45: 45943 | B45: 412 | C45: 0 | D45: 0 | E45: =sum(B45:C45:D45) -> 412
A46: 45944 | B46: 400 | C46: 0 | D46: 0 | E46: =sum(B46:C46:D46) -> 400
A47: 45945 | B47: 450 | C47: 0 | D47: 298 | E47: =sum(B47:C47:D47) -> 748
A48: 45946 | B48: 760 | C48: 0 | D48: 1268 | E48: =sum(B48:C48:D48) -> 2028
A49: 45947 | B49: 308 | C49: 618 | D49: 0 | E49: =sum(B49:C49:D49) -> 926
A50: 45948 | B50: 1870 | C50: 0 | D50: 825 | E50: =sum(B50:C50:D50) -> 2695
A51: 45949 | B51: 0 | C51: 0 | D51: 0 | E51: =sum(B51:C51:D51) -> 0 | F51: closed
A52: 45950 | B52: 746 | C52: 0 | D52: 169 | E52: =sum(B52:C52:D52) -> 915
A53: 45951 | B53: 785 | C53: 0 | D53: 0 | E53: =sum(B53:C53:D53) -> 785
A54: 45952 | B54: 303 | C54: 656 | D54: 0 | E54: =sum(B54:C54:D54) -> 959
A55: 45953 | B55: 450 | C55: 0 | D55: 0 | E55: =sum(B55:C55:D55) -> 450
A56: 45954 | B56: 492 | C56: 0 | D56: 0 | E56: =sum(B56:C56:D56) -> 492
A57: 45955 | B57: 748 | C57: 200 | D57: 0 | E57: =sum(B57:C57:D57) -> 948
A58: 45956 | B58: 0 | C58: 0 | D58: 0 | E58: =sum(B58:C58:D58) -> 0 | F58: closed
A59: 45957 | B59: 280 | C59: 25 | D59: 0 | E59: =sum(B59:C59:D59) -> 305
A60: 45958 | B60: 1143 | C60: 0 | D60: 0 | E60: =sum(B60:C60:D60) -> 1143
A61: 45959 | B61: 1913 | C61: 546 | D61: 0 | E61: =sum(B61:C61:D61) -> 2459
A62: 45960 | B62: 395 | C62: 507 | D62: 785 | E62: =sum(B62:C62:D62) -> 1687
A63: 45961 | B63: 188 | C63: 99 | D63: 0 | E63: =sum(B63:C63:D63) -> 287
A64: Total | B64: 20485 | C64: 4041 | D64: 4, 170 | E64: =sum(E33:E63) -> 28696
A65: Date | B65: COH Sales | C65: GCash Sales | D65: Food panda Sales | E65: Total Sales | F65: Remarks
A66: 45962 | B66: 0 | C66: 0 | D66: 0 | E66: =sum(B66:C66:D66) -> 0 | F66: closed
A67: 45963 | B67: 0 | C67: 0 | D67: 0 | E67: =sum(B67:C67:D67) -> 0 | F67: closed
A68: 45964 | B68: 0 | C68: 0 | D68: 0 | E68: =sum(B68:C68:D68) -> 0 | F68: closed
A69: 45965 | B69: 0 | C69: 0 | D69: 0 | E69: =sum(B69:C69:D69) -> 0 | F69: closed
A70: 45966 | B70: 0 | C70: 0 | D70: 0 | E70: =sum(B70:C70:D70) -> 0 | F70: closed
A71: 45967 | B71: 0 | C71: 0 | D71: 0 | E71: =sum(B71:C71:D71) -> 0 | F71: closed
A72: 45968 | B72: 0 | C72: 0 | D72: 0 | E72: =sum(B72:C72:D72) -> 0 | F72: closed
A73: 45969 | B73: 0 | C73: 0 | D73: 0 | E73: =sum(B73:C73:D73) -> 0 | F73: closed
A74: 45970 | B74: 0 | C74: 0 | D74: 0 | E74: =sum(B74:C74:D74) -> 0 | F74: closed
A75: 45971 | B75: 1481 | C75: 0 | D75: 0 | E75: =sum(B75:C75:D75) -> 1481
A76: 45972 | B76: 745 | C76: 894 | D76: 0 | E76: =sum(B76:C76:D76) -> 1639
A77: 45973 | B77: 635 | C77: 149 | D77: 363 | E77: =sum(B77:C77:D77) -> 1147
A78: 45974 | B78: 2603 | C78: 522 | D78: 0 | E78: =sum(B78:C78:D78) -> 3125
A79: 45975 | B79: 1445 | C79: 596 | D79: 0 | E79: =sum(B79:C79:D79) -> 2041
A80: 45976 | B80: 357 | C80: 0 | D80: 298 | E80: =sum(B80:C80:D80) -> 655
A81: 45977 | B81: 0 | C81: 0 | D81: 0 | E81: =sum(B81:C81:D81) -> 0 | F81: closed
A82: 45978 | B82: 1566 | C82: 0 | D82: 445 | E82: =sum(B82:C82:D82) -> 2011
A83: 45979 | B83: 1381 | C83: 75 | D83: 248 | E83: =sum(B83:C83:D83) -> 1704
A84: 45980 | B84: 930 | C84: 238 | D84: 0 | E84: =sum(B84:C84:D84) -> 1168
A85: 45981 | B85: 302 | C85: 0 | D85: 298 | E85: =sum(B85:C85:D85) -> 600
A86: 45982 | B86: 1605 | C86: 189 | D86: 338 | E86: =sum(B86:C86:D86) -> 2132
A87: 45983 | B87: 745 | C87: 447 | D87: 0 | E87: =sum(B87:C87:D87) -> 1192
A88: 45984 | B88: 0 | C88: 0 | D88: 0 | E88: =sum(B88:C88:D88) -> 0 | F88: closed
A89: 45985 | B89: 1465 | C89: 347 | D89: 149 | E89: =sum(B89:C89:D89) -> 1961
A90: 45986 | B90: 238 | C90: 298 | D90: 0 | E90: =sum(B90:C90:D90) -> 536
A91: 45987 | B91: 805 | C91: 0 | D91: 0 | E91: =sum(B91:C91:D91) -> 805
A92: 45988 | B92: 1896 | C92: 0 | D92: 0 | E92: =sum(B92:C92:D92) -> 1896
A93: 45989 | B93: 2131 | C93: 0 | D93: 0 | E93: =sum(B93:C93:D93) -> 2131
A94: 45990 | B94: 163 | C94: 0 | D94: 149 | E94: =sum(B94:C94:D94) -> 312
A95: 45991 | B95: 0 | C95: 0 | D95: 0 | E95: =B95+C95+D95 -> 0 | F95: closed
A96: Total | B96: 20493 | C96: 3755 | D96: 2288 | E96: =sum(E66:E95) -> 26536
A98: Date | B98: Cash Sales | C98: GCash Sales | D98: Foodpanda Sales | E98: Total Sales | F98: Expenses from kaha | G98: COH | H98: Petty Cash | I98: Remarks
A99: 45992 | B99: 0 | C99: 0 | D99: 0 | E99: =IF(B99+C99+D99=0,"",B99+C99+D99) | G99: =IF(B99="","",B99-IF(F99="",0,F99)) -> 0 | H99: 0
A100: 45993 | B100: 0 | C100: 0 | D100: 0 | E100: =IF(B100+C100+D100=0,"",B100+C100+D100) | G100: =IF(B100="","",B100-IF(F100="",0,F100)) -> 0 | H100: 0
A101: 45994 | B101: 0 | C101: 0 | D101: 0 | E101: =IF(B101+C101+D101=0,"",B101+C101+D101) | G101: =IF(B101="","",B101-IF(F101="",0,F101)) -> 0 | H101: 0
A102: 45995 | B102: 0 | C102: 0 | D102: 0 | E102: =IF(B102+C102+D102=0,"",B102+C102+D102) | G102: =IF(B102="","",B102-IF(F102="",0,F102)) -> 0 | H102: 0
A103: 45996 | B103: 0 | C103: 0 | D103: 0 | E103: =IF(B103+C103+D103=0,"",B103+C103+D103) | G103: =IF(B103="","",B103-IF(F103="",0,F103)) -> 0 | H103: 0
A104: 45997 | B104: 0 | C104: 0 | D104: 0 | E104: =IF(B104+C104+D104=0,"",B104+C104+D104) | G104: =IF(B104="","",B104-IF(F104="",0,F104)) -> 0 | H104: 0
A105: 45998 | B105: 0 | C105: 0 | D105: 0 | E105: =IF(B105+C105+D105=0,"",B105+C105+D105) | G105: =IF(B105="","",B105-IF(F105="",0,F105)) -> 0 | H105: 0
A106: 45999 | B106: 0 | C106: 0 | D106: 0 | E106: =IF(B106+C106+D106=0,"",B106+C106+D106) | G106: =IF(B106="","",B106-IF(F106="",0,F106)) -> 0 | H106: 0 | I106: CLOSED
A107: 46000 | B107: 0 | C107: 0 | D107: 0 | E107: =IF(B107+C107+D107=0,"",B107+C107+D107) | G107: =IF(B107="","",B107-IF(F107="",0,F107)) -> 0 | H107: 0
A108: 46001 | B108: =IFERROR(SUMIF(DailySales!$L:$L,$A108,DailySales!$E:$E),0) -> 805 | C108: =IFERROR(SUMIF(DailySales!$L:$L,$A108,DailySales!$G:$G),0) -> 805 | D108: =IFERROR(SUMIF(DailySales!$L:$L,$A108,DailySales!$I:$I),0) -> 0 | E108: =IF(B108+C108+D108=0,"",B108+C108+D108) -> 1610 | F108: 50 | G108: =IF(B108="","",B108-IF(F108="",0,F108)) -> 755 | H108: 0
A109: 46002 | B109: =IFERROR(SUMIF(DailySales!$L:$L,$A109,DailySales!$E:$E),0) -> 944 | C109: =IFERROR(SUMIF(DailySales!$L:$L,$A109,DailySales!$G:$G),0) -> 0 | D109: =IFERROR(SUMIF(DailySales!$L:$L,$A109,DailySales!$I:$I),0) -> 477 | E109: =IF(B109+C109+D109=0,"",B109+C109+D109) -> 1421 | G109: =IF(B109="","",B109-IF(F109="",0,F109)) -> 944 | H109: 0
A110: 46003 | B110: =IFERROR(SUMIF(DailySales!$L:$L,$A110,DailySales!$E:$E),0) -> 1181 | C110: =IFERROR(SUMIF(DailySales!$L:$L,$A110,DailySales!$G:$G),0) -> 636 | D110: =IFERROR(SUMIF(DailySales!$L:$L,$A110,DailySales!$I:$I),0) -> 0 | E110: =IF(B110+C110+D110=0,"",B110+C110+D110) -> 1817 | F110: 200 | G110: =IF(B110="","",B110-IF(F110="",0,F110)) -> 981 | H110: 50
...

Sheet Inventory
A1: Date | B1: Item | C1: Category | D1: Quantity | E1: Unit | F1: Cost per Unit (₱) | G1: Total Cost (₱) | H1: Supplier / Store | I1: Notes
A2: 45903 | B2: lamas, dishwashing, sugar | C2: supplies | G2: 301
A3: 45905 | B3: egg, softdrinks | C3: supplies | G3: 1119
A4: 45912 | B4: pork, chicken | C4: supplies | G4: 1440
A5: 45913 | B5: softdrinks | C5: supplies | G5: 870
A6: 45924 | B6: belly, porkchop, c.breast, carrots, pepino, cabbage, cheese, vetsin, calamansi, spring onions, mantika, itlog | C6: supplies | G6: 3290
A7: 45926 | B7: softdrinks, sugar | C7: supplies | G7: 1469
A8: 45934 | B8: egg, rice | C8: supplies | G8: 769
A9: 45938 | B9: bugas, parcel(476), Aldrin(700) | C9: supplies | G9: 1309 | I9: includes staff CA Aldrin 700
A10: 45941 | B10: softdrinks, egg, springonions | C10: supplies | G10: 1860
A11: 45942 | B11: vetsin, dishwashing, Aldrin(500) | C11: supplies | G11: 575 | I11: includes staff CA Aldrin 500
A12: 45950 | B12: SM (2,930), Libertad (2,690) | C12: supplies | G12: 5620 | I12: SM + Libertad
A13: 45952 | B13: dishwashing | C13: supplies | G13: 45
A14: 45953 | B14: Water (120), Softdrinks (1160) | C14: supplies | G14: 1280
A15: 45958 | B15: Rice, pork | C15: supplies | G15: 650
A16: 45960 | B16: SM (Meat, ramen, sauce) | C16: supplies | G16: 1759 | I16: SM
A17: 45970 | B17: Grocery | C17: supplies | G17: 2000 | I17: payment: Card
A18: 45978 | B18: Egg, Calamansi | C18: supplies | G18: 580
A19: 45980 | B19: Rice 75, Grocery 2000 | C19: supplies | G19: 2075
A20: 45987 | B20: Egg 2 tray(480), Pork (243), Lamas (240) | C20: supplies | G20: 963
A21: 45991 | B21: Meat | C21: supplies | G21: 2000 | I21: payment: Atome
A22: 46001 | B22: tarp and takeoutboxes | C22: supplies | G22: 1885
A23: 46004 | B23: mt dew. 3 case | C23: supplies | D23: 3 | E23: case | G23: 870
A24: 46004 | B24: egg | C24: supplies | G24: 270
A25: 46004 | B25: pork | C25: supplies | G25: 500
A26: 46004 | B26: chicken | C26: supplies | G26: 206
A27: 46004 | B27: cabbage, carrots,salt | C27: supplies | G27: 340
A28: 46004 | B28: dry peas and corn | C28: supplies | G28: 71
A29: 46006 | B29: rice | C29: supplies | G29: 150
A30: 46009 | B30: beef | C30: supplies | D30: 1.3 | E30: kg | G30: 709
A31: 46009 | B31: rice | C31: supplies | D31: 2 | E31: kg | G31: 104
A32: 46009 | B32: pork | C32: supplies | D32: 0.5 | E32: kg | G32: 170
A33: 46013 | B33: pork | C33: supplies | D33: 0.8 | E33: kg | G33: 280
A34: 46013 | B34: fish fillet | C34: supplies | D34: 3 | E34: pcs | G34: 114
A35: 46013 | B35: butter | C35: supplies | D35: 2 | E35: bar | G35: 108
A36: 46013 | B36: chicken wings | C36: supplies | D36: 1 | E36: kg | G36: 259
A37: 46013 | B37: flour,cabbage,hotdog,trapo | C37: supplies | G37: 338
A38: 46014 | B38: Onion, carrots | C38: supplies | G38: 100

Sheet Expenses
A1: Date | B1: Category | C1: Description | D1: Payment Method | E1: Amount (₱) | F1: Remarks
A2: 45915 | B2: utilities | C2: electricity bill, water | D2: gcash | E2: 5982.22
A3: 45917 | B3: staff | C3: Aldrin | D3: gcash | E3: 4800
A4: 45925 | B4: staff | C4: Aldrin | D4: cash | E4: 800
A5: 45930 | B5: staff | C5: Aldrin | D5: cash | E5: 7200
A6: 45944 | B6: staff | C6: cash advance (Ken) | D6: cash | E6: 150
A7: 45945 | B7: staff | C7: Ken (1500), Aldrin (4500) | D7: cash | E7: 5500
A8: 45947 | B8: staff | C8: Ken (900) | D8: cash | E8: 900
A9: 45948 | B9: staff | C9: Ken (450) | D9: cash | E9: 450
A10: 45951 | B10: staff | C10: Aldrin (600) CA | D10: cash | E10: 600
A11: 45954 | B11: staff | C11: CA Ken (400), Aldrin (200) | D11: cash | E11: 600
A12: 45955 | B12: supplies | C12: CA Aldrin (500), Receipt (171) | D12: cash | E12: 671
A13: 45957 | B13: supplies | C13: Rice, Aldrin (270), Ken (150) | D13: cash | E13: 570
... A26: 46008 | B26: utilities | C26: wifi | D26: cash | E26: 1000
A27: 46008 | B27: staff | C27: aldrin sweldo 4260 | D27: cash
A28: 46009 | B28: supplies | C28: Pork, sugar,green peas, rice, gochujhang | D28: cash | E28: 664
A29: 46009 | B29: supplies | C29: Beef(659) tissue(50) | D29: FP sales
A30: 46013 | B30: supplies | C30: meat, veges, bugas, trapo | D30: cash | E30: 1401
A31: 46013 | B31: staff | C31: guard | D31: cash | E31: 800
B32: familyv expenses | C32: chicken, pork,grocery, athena | D32: cash | E32: 704

Sheet StockInOut
A1: Date | B1: Item | C1: Type | D1: Qty | E1: Unit | F1: Reason | G1: Reference | H1: Notes
A2: 46003 | B2: egg | C2: IN | D2: 2 | E2: tray | F2: purchase
A3: 46004 | B3: egg | C3: IN | D3: 1 | E3: tray | F3: purchase
A4: 46004 | B4: pork | C4: IN | D4: 1.5 | E4: PO | F4: purchase
A5: 46004 | B5: softdrinks | C5: IN | D5: 74 | E5: pcs | F5: purchase
A6: 46004 | B6: chicken | C6: IN | D6: 1 | E6: kg | F6: purchase
A7: 46006 | B7: rice | C7: IN | D7: 1 | E7: kg | F7: purchase
A8: 46008 | B8: chicken | C8: IN | D8: 1.5 | E8: kg | F8: purchase
A9: 46008 | B9: pork | C9: IN | D9: 1.5 | E9: kg | F9: purchase
A10: 46009 | B10: Beef | C10: IN | D10: 900 | E10: g | F10: purchase
A11: 46009 | B11: Pork | C11: IN | D11: 0.5 | E11: kg | F11: Purchase
A12: 46009 | B12: Rice | C12: IN | D12: 2 | E12: kg | F12: Purchase
A13: 46013 | B13: chicken wings | C13: IN | D13: 1 | E13: kg | F13: Purchase
... A16: 46015 | B16: Fish fillet | C16: IN | D16: 3 | E16: pcs | F16: Purchase
A17: 46016
A18: 46017
A19: 46018
A20: 46019
A21: 46020
A22: 46021
A23: 46022
A24: 46023
A25: 46024
A26: 46025
A27: 46026
A28: 46027
... A43: 46042

Sheet StockBalance
A1: Item | B1: Unit | C1: Total In | D1: Total Out | E1: Balance
A2: Pork | B2: kg | C2: =IFERROR(SUMIFS(StockInOut!$D:$D,StockInOut!$B:$B,$A2,StockInOut!$C:$C,"IN"),0) -> 4 | D2: =IFERROR(SUMIFS(StockInOut!$D:$D,StockInOut!$B:$B,$A2,StockInOut!$C:$C,"OUT"),0) -> 0 | E2: =C2-D2 -> 4
A3: Chicken | B3: kg | C3: =IFERROR(SUMIFS(StockInOut!$D:$D,StockInOut!$B:$B,$A3,StockInOut!$C:$C,"IN"),0) -> 2.5 | D3: =IFERROR(SUMIFS(StockInOut!$D:$D,StockInOut!$B:$B,$A3,StockInOut!$C:$C,"OUT"),0) -> 0 | E3: =C3-D3 -> 2.5
A4: Beef | B4: kg | C4: =IFERROR(SUMIFS(StockInOut!$D:$D,StockInOut!$B:$B,$A4,StockInOut!$C:$C,"IN"),0) -> 900 | D4: =IFERROR(SUMIFS(StockInOut!$D:$D,StockInOut!$B:$B,$A4,StockInOut!$C:$C,"OUT"),0) -> 0 | E4: =C4-D4 -> 900
A5: Squid | B5: kg | C5: =IFERROR(SUMIFS(StockInOut!$D:$D,StockInOut!$B:$B,$A5,StockInOut!$C:$C,"IN"),0) -> 0 | D5: =IFERROR(SUMIFS(StockInOut!$D:$D,StockInOut!$B:$B,$A5,StockInOut!$C:$C,"OUT"),0) -> 0 | E5: =C5-D5 -> 0
A6: Rice | B6: kg | C6: =IFERROR(SUMIFS(StockInOut!$D:$D,StockInOut!$B:$B,$A6,StockInOut!$C:$C,"IN"),0) -> 8 | D6: =IFERROR(SUMIFS(StockInOut!$D:$D,StockInOut!$B:$B,$A6,StockInOut!$C:$C,"OUT"),0) -> 0 | E6: =C6-D6 -> 8
A7: Egg | B7: tray | C7: =IFERROR(SUMIFS(StockInOut!$D:$D,StockInOut!$B:$B,$A7,StockInOut!$C:$C,"IN"),0) -> 3 | D7: =IFERROR(SUMIFS(StockInOut!$D:$D,StockInOut!$B:$B,$A7,StockInOut!$C:$C,"OUT"),0) -> 0 | E7: =C7-D7 -> 3
A8: Softdrinks | B8: bottle | C8: =IFERROR(SUMIFS(StockInOut!$D:$D,StockInOut!$B:$B,$A8,StockInOut!$C:$C,"IN"),0) -> 74 | D8: =IFERROR(SUMIFS(StockInOut!$D:$D,StockInOut!$B:$B,$A8,StockInOut!$C:$C,"OUT"),0) -> 0 | E8: =C8-D8 -> 74
A9: Oil | B9: L | C9: =IFERROR(SUMIFS(StockInOut!$D:$D,StockInOut!$B:$B,$A9,StockInOut!$C:$C,"IN"),0) -> 0 | D9: =IFERROR(SUMIFS(StockInOut!$D:$D,StockInOut!$B:$B,$A9,StockInOut!$C:$C,"OUT"),0) -> 0 | E9: =C9-D9 -> 0

Sheet MonthlySummary
A1: Month | B1: Sales (Summary!E) | C1: Supplies (Inventory!G) | D1: Overhead (Expenses!E) | E1: Total Expenses | F1: Profit | G1: Notes
A2: 45901 | B2: =SUMIFS(DailySummary!$E:$E,DailySummary!$A:$A,">="&EOMONTH($A2,-1)+1,DailySummary!$A:$A,"<="&EOMONTH($A2,0)) -> 38912 | C2: =SUMIFS(Inventory!$G:$G,Inventory!$A:$A,">="&EOMONTH($A2,-1)+1,Inventory!$A:$A,"<="&EOMONTH($A2,0)) -> 8489 | D2: =SUMIFS(Expenses!$E:$E,Expenses!$A:$A,">="&EOMONTH($A2,-1)+1,Expenses!$A:$A,"<="&EOMONTH($A2,0)) -> 18782.22 | E2: =C2+D2 -> 27271.22 | F2: =B2-E2 -> 11640.78
A3: 45931 | B3: =SUMIFS(DailySummary!$E:$E,DailySummary!$A:$A,">="&EOMONTH($A3,-1)+1,DailySummary!$A:$A,"<="&EOMONTH($A3,0)) -> 28696 | C3: =SUMIFS(Inventory!$G:$G,Inventory!$A:$A,">="&EOMONTH($A3,-1)+1,Inventory!$A:$A,"<="&EOMONTH($A3,0)) -> 13867 | D3: =SUMIFS(Expenses!$E:$E,Expenses!$A:$A,">="&EOMONTH($A3,-1)+1,Expenses!$A:$A,"<="&EOMONTH($A3,0)) -> 9441 | E3: =C3+D3 -> 23308 | F3: =B3-E3 -> 5388
A4: 45962 | B4: =SUMIFS(DailySummary!$E:$E,DailySummary!$A:$A,">="&EOMONTH($A4,-1)+1,DailySummary!$A:$A,"<="&EOMONTH($A4,0)) -> 26536 | C4: =SUMIFS(Inventory!$G:$G,Inventory!$A:$A,">="&EOMONTH($A4,-1)+1,Inventory!$A:$A,"<="&EOMONTH($A4,0)) -> 7618 | D4: =SUMIFS(Expenses!$E:$E,Expenses!$A:$A,">="&EOMONTH($A4,-1)+1,Expenses!$A:$A,"<="&EOMONTH($A4,0)) -> 7819 | E4: =C4+D4 -> 15437 | F4: =B4-E4 -> 11099
A5: 45992 | B5: =SUMIFS(DailySummary!$E:$E,DailySummary!$A:$A,">="&EOMONTH($A5,-1)+1,DailySummary!$A:$A,"<="&EOMONTH($A5,0)) -> 17052 | C5: =SUMIFS(Inventory!$G:$G,Inventory!$A:$A,">="&EOMONTH($A5,-1)+1,Inventory!$A:$A,"<="&EOMONTH($A5,0)) -> 6474 | D5: =SUMIFS(Expenses!$E:$E,Expenses!$A:$A,">="&EOMONTH($A5,-1)+1,Expenses!$A:$A,"<="&EOMONTH($A5,0)) -> 5890 | E5: =C5+D5 -> 12364 | F5: =B5-E5 -> 4688
A6: 46023 | B6: =SUMIFS(DailySummary!$E:$E,DailySummary!$A:$A,">="&EOMONTH($A6,-1)+1,DailySummary!$A:$A,"<="&EOMONTH($A6,0)) -> 0 | C6: =SUMIFS(Inventory!$G:$G,Inventory!$A:$A,">="&EOMONTH($A6,-1)+1,Inventory!$A:$A,"<="&EOMONTH($A6,0)) -> 0 | D6: =SUMIFS(Expenses!$E:$E,Expenses!$A:$A,">="&EOMONTH($A6,-1)+1,Expenses!$A:$A,"<="&EOMONTH($A6,0)) -> 0 | E6: =C6+D6 -> 0 | F6: =B6-E6 -> 0
A7: 46082 | B7: =SUMIFS(DailySummary!$E:$E,DailySummary!$A:$A,">="&EOMONTH($A7,-1)+1,DailySummary!$A:$A,"<="&EOMONTH($A7,0)) -> 0 | C7: =SUMIFS(Inventory!$G:$G,Inventory!$A:$A,">="&EOMONTH($A7,-1)+1,Inventory!$A:$A,"<="&EOMONTH($A7,0)) -> 0 | D7: =SUMIFS(Expenses!$E:$E,Expenses!$A:$A,">="&EOMONTH($A7,-1)+1,Expenses!$A:$A,"<="&EOMONTH($A7,0)) -> 0 | E7: =C7+D7 -> 0 | F7: =B7-E7 -> 0
A8: 46113 | B8: =SUMIFS(DailySummary!$E:$E,DailySummary!$A:$A,">="&EOMONTH($A8,-1)+1,DailySummary!$A:$A,"<="&EOMONTH($A8,0)) -> 0 | C8: =SUMIFS(Inventory!$G:$G,Inventory!$A:$A,">="&EOMONTH($A8,-1)+1,Inventory!$A:$A,"<="&EOMONTH($A8,0)) -> 0 | D8: =SUMIFS(Expenses!$E:$E,Expenses!$A:$A,">="&EOMONTH($A8,-1)+1,Expenses!$A:$A,"<="&EOMONTH($A8,0)) -> 0 | E8: =C8+D8 -> 0 | F8: =B8-E8 -> 0
A9: 46143 | B9: =SUMIFS(DailySummary!$E:$E,DailySummary!$A:$A,">="&EOMONTH($A9,-1)+1,DailySummary!$A:$A,"<="&EOMONTH($A9,0)) -> 0 | C9: =SUMIFS(Inventory!$G:$G,Inventory!$A:$A,">="&EOMONTH($A9,-1)+1,Inventory!$A:$A,"<="&EOMONTH($A9,0)) -> 0 | D9: =SUMIFS(Expenses!$E:$E,Expenses!$A:$A,">="&EOMONTH($A9,-1)+1,Expenses!$A:$A,"<="&EOMONTH($A9,0)) -> 0 | E9: =C9+D9 -> 0 | F9: =B9-E9 -> 0
